carconnectivity_connector_audi-0.2.2.dist-info/licenses/LICENSE
carconnectivity_connectors/audi/__init__.py
carconnectivity_connectors/audi/_version.py
carconnectivity_connectors/audi/capability.py
carconnectivity_connectors/audi/charging.py
carconnectivity_connectors/audi/climatization.py
carconnectivity_connectors/audi/command_impl.py
carconnectivity_connectors/audi/connector.py
carconnectivity_connectors/audi/vehicle.py
carconnectivity_connectors/audi/auth/__init__.py
carconnectivity_connectors/audi/auth/audi_web_session.py
carconnectivity_connectors/audi/auth/auth_util.py
carconnectivity_connectors/audi/auth/openid_session.py
carconnectivity_connectors/audi/auth/session_manager.py
carconnectivity_connectors/audi/auth/we_connect_session_audi.py
carconnectivity_connectors/audi/auth/helpers/blacklist_retry.py
carconnectivity_connectors/audi/ui/connector_ui.py
carconnectivity_connector_audi-0.2.2.dist-info/METADATA
carconnectivity_connector_audi-0.2.2.dist-info/WHEEL
carconnectivity_connector_audi-0.2.2.dist-info/top_level.txt
carconnectivity_connector_audi-0.2.2.dist-info/RECORD
