Metadata-Version: 2.4
Name: carconnectivity-connector-audi
Version: 0.2.2
Summary: CarConnectivity connector for Audi services - integrates with Till Steinbach's CarConnectivity framework
Author: Achim Fischer based on work of Till Steinbach
License-Expression: MIT
Project-URL: Homepage, https://github.com/acfischer42/CarConnectivity-connector-audi
Project-URL: Repository, https://github.com/acfischer42/CarConnectivity-connector-audi
Project-URL: Issues, https://github.com/acfischer42/CarConnectivity-connector-audi/issues
Project-URL: CarConnectivity Framework, https://github.com/tillsteinbach/CarConnectivity
Project-URL: CarConnectivity CLI, https://github.com/tillsteinbach/CarConnectivity-cli
Keywords: audi,car,connectivity,api,myaudi,automotive,carconnectivity
Classifier: Development Status :: 3 - Alpha
Classifier: Intended Audience :: Developers
Classifier: Programming Language :: Python :: 3.9
Classifier: Programming Language :: Python :: 3.10
Classifier: Programming Language :: Python :: 3.11
Classifier: Programming Language :: Python :: 3.12
Classifier: Programming Language :: Python :: 3.13
Classifier: Topic :: Software Development :: Libraries
Classifier: Topic :: Home Automation
Classifier: Topic :: Internet :: WWW/HTTP :: Dynamic Content
Requires-Python: >=3.9
License-File: LICENSE
Requires-Dist: carconnectivity>=0.11
Requires-Dist: oauthlib~=3.3.1
Requires-Dist: requests~=2.32.3
Requires-Dist: pyjwt~=2.10
Dynamic: license-file
